omniblack/hatch/__init__.py
omniblack_hatch-0.0.10.dist-info/METADATA
omniblack_hatch-0.0.10.dist-info/WHEEL
omniblack_hatch-0.0.10.dist-info/entry_points.txt
omniblack_hatch-0.0.10.dist-info/licenses/LICENSE.txt
omniblack_hatch-0.0.10.dist-info/RECORD
