Metadata-Version: 2.4
Name: omniblack.hatch
Version: 0.0.10
Summary: Library that helps package omniblack packages.
Project-URL: Homepage, https://gitlab.com/terryp/terry/-/tree/next/tooling/hatch
Project-URL: Repository, https://gitlab.com/terryp/terry.git
Author-email: Terry Patterson <Terryp@wegrok.net>
License-Expression: Apache-2.0
License-File: LICENSE.txt
Classifier: Development Status :: 3 - Alpha
Classifier: Framework :: Hatch
Classifier: Intended Audience :: Developers
Requires-Python: >=3.12
Requires-Dist: hatchling~=1.21
